README.md
setup.py
pathliberty/__init__.py
pathliberty/_version.py
pathliberty/base.py
pathliberty/cli.py
pathliberty/local_path.py
pathliberty/remote_path.py
pathliberty/ssh.py
pathliberty/ssh_config.py
pathliberty/ssh_path.py
pathliberty.egg-info/PKG-INFO
pathliberty.egg-info/SOURCES.txt
pathliberty.egg-info/dependency_links.txt
pathliberty.egg-info/requires.txt
pathliberty.egg-info/top_level.txt